lsmeta_pydantic/__init__.py
lsmeta_pydantic-1.0.0.dist-info/METADATA
lsmeta_pydantic-1.0.0.dist-info/WHEEL
lsmeta_pydantic-1.0.0.dist-info/RECORD
