Metadata-Version: 2.1
Name: lsmeta-pydantic
Version: 1.0.0
Summary: Meta package for pydantic
Author: Your Name
Author-email: you@example.com
Requires-Python: >=3.11,<4.0
Classifier: Programming Language :: Python :: 3
Classifier: Programming Language :: Python :: 3.11
Requires-Dist: pydantic (>=2.4.2,<3.0.0)
